Metadata-Version: 1.0
Name: metrofunction
Version: 0.2
Summary: A function that can predict the cost of metro construction
Home-page: http://github.com/storborg/metrofunction
Author: Manolo
Author-email: manolo@example.com
License: MIT
Platform: UNKNOWN
